odoo/addons/printing_simple_configuration/README.rst
odoo/addons/printing_simple_configuration/__init__.py
odoo/addons/printing_simple_configuration/__manifest__.py
odoo/addons/printing_simple_configuration/data/demo.xml
odoo/addons/printing_simple_configuration/i18n/es.po
odoo/addons/printing_simple_configuration/i18n/it.po
odoo/addons/printing_simple_configuration/i18n/printing_simple_configuration.pot
odoo/addons/printing_simple_configuration/models/__init__.py
odoo/addons/printing_simple_configuration/models/company.py
odoo/addons/printing_simple_configuration/models/print_config.py
odoo/addons/printing_simple_configuration/models/printer.py
odoo/addons/printing_simple_configuration/readme/DESCRIPTION.rst
odoo/addons/printing_simple_configuration/readme/ROADMAP.rst
odoo/addons/printing_simple_configuration/security/ir.model.access.csv
odoo/addons/printing_simple_configuration/security/security.xml
odoo/addons/printing_simple_configuration/static/description/icon.png
odoo/addons/printing_simple_configuration/static/description/index.html
odoo/addons/printing_simple_configuration/static/description/print_config.png
odoo/addons/printing_simple_configuration/views/company.xml
odoo/addons/printing_simple_configuration/views/print_config.xml
odoo_addon_printing_simple_configuration-16.0.1.1.0.2.dist-info/METADATA
odoo_addon_printing_simple_configuration-16.0.1.1.0.2.dist-info/WHEEL
odoo_addon_printing_simple_configuration-16.0.1.1.0.2.dist-info/top_level.txt
odoo_addon_printing_simple_configuration-16.0.1.1.0.2.dist-info/RECORD
